{"instance_nav":false,"footer":{},"children":[],"jslib":{"hideSyncButtonJs":"function (pageContext) { function arrayCheck(a) { return (typeof a === 'undefined' || a === '' || a.length <= 0); } if (typeof pageContext.hideSyncButton === 'undefined' || pageContext.hideSyncButton === '') { return true; } if(arrayCheck(pageContext.inventoryRequestData) && arrayCheck(pageContext.transferOrderData) && arrayCheck(pageContext.returnOrderData)){ return true; } return (pageContext.hideSyncButton); }"},"header":{"leftButton":{"id":"aHeadLeft","title":"X","enabled":true}},"id":"fseInventoryLandingPage","title":"{%myInventory}","actions":{"navigationToSamePage":{"pageId":"fseInventoryLandingPage","type":"navigation"},"publishMultiActionSyncEvent":{"type":"api","apiObject":{"data":[{"eventId":"multiActionSyncTo-IR-TO-RO-Event","contextVar":{"inventoryRequestData":"@pageContext.inventoryRequestData","currentUserId":"@pageContext.__sys__loggedIn_UserId","roDataVersion":"@pageContext.roDataVersion","returnOrderData":"@pageContext.returnOrderData","toDataVersion":"@pageContext.toDataVersion","irDataVersion":"@pageContext.irDataVersion","truckAssignedToUser":"@pageContext.truckAssignedToUser","transferOrderData":"@pageContext.transferOrderData"}}]},"url":"/event/start"},"hideSyncButton":{"beforeUpdate":[{"updateKeys":["hideSyncButton"],"jslib":"function(pageContext){return(true);}"}],"type":"beforeJsUpdate"}},"cols":[{"body":[{"endColumn":11,"startColumn":0,"index":1,"id":"inventoryContentBox","type":"contentbox","content":[{"endColumn":11,"hidden":false,"startColumn":0,"index":1,"id":"truckAssigned","fontStyle":"standard","type":"paragraphText","alignment":"left","title":"{%truckAssigned}","value":"@pageContext.truckAssignedToUser[0].siteName","enabled":1,"required":0},{"endColumn":11,"hidden":false,"startColumn":0,"dataType":"datetime","id":"lastSyncTime","fontStyle":"standard","type":"paragraphText","alignment":"left","title":"{%lastSyncTime}","value":"@pageContext.truckLastUpdated","enabled":1,"required":0}]},{"allowDelete":0,"endColumn":11,"hidden":false,"heading":"{%myInventory}","indexName":"","columns":[{"col":1,"name":"{%mnmn}","row":1,"key":"catalogNameModelNumber"},{"col":2,"name":"{%manufacturer}","row":1,"key":"manufacturerName"},{"col":3,"name":"{%tq}","row":1,"key":"inventoryQuantity"}],"editable":1,"index":2,"type":"datagrid","title":"{%onHand}","isAutoSave":true,"required":0,"editRowPageId":"fseOnHandDetailsEditPage","startColumn":0,"addRowPageId":"","disableAdd":true,"id":"fseOnHandDataGrid","value":"@pageContext.onHandData"},{"allowDelete":0,"endColumn":11,"indexName":"","columns":[{"col":1,"name":"{%status}","row":1,"key":"transferOrderStatusName"},{"col":2,"name":"{%toi}","row":1,"key":"transferOrderId"},{"col":3,"name":"{%details}","row":1,"key":"catalogDetails"}],"editable":1,"index":3,"type":"datagrid","title":"{%transferOrders}","isAutoSave":false,"required":0,"editRowPageId":"fseTransferOrderDetailsEditPage","startColumn":0,"addRowPageId":"","disableAdd":true,"id":"fseTransferOrderDataGrid","value":"@pageContext.transferOrderData"},{"allowDelete":0,"endColumn":11,"hidden":false,"heading":"{%myRequests}","indexName":"","columns":[{"col":1,"name":"{%ri1}","row":1,"key":"inventoryRequestId"},{"col":2,"name":"{%mn}","row":1,"key":"irCatalogValue[0].modelName"},{"col":3,"dataType":"datetime","name":"{%rdt}","row":1,"key":"deliverBy"},{"col":4,"name":"{%status}","row":1,"key":"status"}],"editable":1,"index":4,"type":"datagrid","title":"{%inventoryRequest}","isAutoSave":false,"required":0,"editRowPageId":"fseIREditPage","startColumn":0,"addRowPageId":"fseIRAddPage","id":"fseInventoryRequestDataGrid","value":"@pageContext.inventoryRequestData"},{"allowDelete":0,"endColumn":11,"hidden":false,"indexName":"","columns":[{"col":1,"name":"{%oi}","row":1,"key":"returnOrderId"},{"col":2,"dataType":"datetime","name":"{%rd1}","row":1,"key":"returnOrderRequestedDate"},{"col":3,"name":"{%status}","row":1,"key":"returnOrderStatusName"}],"editable":1,"index":5,"type":"datagrid","title":"{%returnOrders}","isAutoSave":false,"required":0,"editRowPageId":"fseROEditPage","startColumn":0,"addRowPageId":"fseROAddPage","id":"fseReturnOrderDataGrid","value":"@pageContext.returnOrderData"},{"endColumn":11,"hidden":"@js.hideSyncButtonJs","startColumn":0,"index":6,"action":"multiAction","id":"mab3","capturedTime":"","type":"button","title":"{%sn6}","multiActionOnClick":["publishMultiActionSyncEvent","hideSyncButton"]}],"span":1}]}