{"dynamicFilter":{},"isScrollAble":true,"deleteAllowed":false,"searchAllowed":true,"tableWidth":"170rem","searchEmptyScreen":{"image":"@iconlib.ActionsSearchError","contentValue":"@lang.['sysrcue','SORRY! YOUR SEARCH RESULTS CAME UP EMPTY ']","type":"noData"},"rowActions":{},"modifyRowActions":[],"gridRefreshId":"billingReportGrid","emptyScreen":{"image":"@iconlib.ActionsSearchEmpty","contentValue":"@lang.['ylieatm','YOUR LIST IS EMPTY AT THE MOMENT']","type":"noData"},"isSync":true,"tableHeader":[{"options":{"flex":1.3,"sortOrder":"ASC","currentSorted":false,"sortable":false,"showLabel":true,"searchable":true},"name":"@lang.['fn01', 'File Number']","key":"acFileNumber"},{"options":{"flex":1.8,"sortOrder":"ASC","currentSorted":false,"sortable":false,"showLabel":true,"searchable":true},"name":"@lang.['spa01', 'Subject Property Address']","key":"address"},{"options":{"flex":1.5,"sortOrder":"ASC","currentSorted":false,"sortable":false,"showLabel":true,"searchable":true},"name":"@lang.['at01', 'Address Two']","key":"addressTwo"},{"options":{"flex":1,"sortOrder":"ASC","currentSorted":false,"sortable":false,"showLabel":true,"searchable":true},"name":"@lang.['c08', 'City']","key":"city"},{"options":{"flex":1,"sortOrder":"ASC","currentSorted":false,"sortable":false,"showLabel":true,"searchable":true},"name":"@lang.['s02', 'State']","key":"state"},{"options":{"flex":1,"sortOrder":"ASC","currentSorted":false,"sortable":false,"showLabel":true,"searchable":true},"name":"@lang.['pc01', 'Postal Code']","key":"postalCode"},{"options":{"flex":1,"sortOrder":"ASC","currentSorted":false,"sortable":false,"showLabel":true,"searchable":true},"name":"@lang.['rt01', 'Report Type']","key":"acReason"},{"options":{"flex":0.8,"sortOrder":"ASC","currentSorted":false,"sortable":false,"showLabel":true,"searchable":true},"name":"@lang.['t01', 'Tags']","key":"acTags"},{"options":{"flex":1,"sortOrder":"ASC","currentSorted":false,"sortable":false,"showLabel":true,"searchable":true},"name":"@lang.['ap01', 'Appraiser']","key":"acPrimaryAppraiserId"},{"options":{"flex":1,"sortOrder":"ASC","currentSorted":false,"sortable":false,"showLabel":true,"searchable":true},"name":"@lang.['an01', 'Analyst']","key":"userName"},{"options":{"flex":1.3,"sortOrder":"ASC","currentSorted":false,"sortable":false,"showLabel":true,"searchable":true},"name":"@lang.['df01', 'Drive From']","key":"driveFromAddress"},{"options":{"flex":1.3,"sortOrder":"ASC","currentSorted":false,"sortable":false,"showLabel":true,"searchable":true},"name":"@lang.['dt02','Drive To']","key":"propertyType"},{"options":{"flex":1.3,"sortOrder":"ASC","currentSorted":false,"sortable":false,"showLabel":true,"searchable":true},"name":"@lang.['dt01', 'Drive Type']","key":"driveType"},{"options":{"flex":1.8,"sortOrder":"ASC","currentSorted":false,"sortable":false,"type":"datetime","showLabel":true,"searchable":true},"name":"@lang.['dst01', 'Drive Start Time']","key":"startTravelDate"},{"options":{"flex":1.8,"sortOrder":"ASC","currentSorted":false,"sortable":false,"type":"datetime","showLabel":true,"searchable":true},"name":"@lang.['det01', 'Drive End Time']","key":"endTravelDate"},{"options":{"flex":1.8,"sortOrder":"ASC","currentSorted":false,"sortable":false,"showLabel":true,"searchable":true},"name":"@lang.['tdt01', 'Total Drive Time']","key":"driveTime"},{"options":{"flex":1.8,"sortOrder":"ASC","currentSorted":false,"sortable":false,"showLabel":true,"searchable":true},"name":"@lang.['dd01', 'Drive Distance']","key":"driveDistance"}],"dataToBeSent":{"apiResponseParams":["count"],"processId":"fetchDriveTimeReportDataWF","apiResponseFormat":true,"contextVar":{},"apiResponseObject":"driveData"},"dataSourceId":"process/start","exportable":true,"sourceType":"api","rowTextLength":20,"jslib":{},"header":{"filterAllowed":false,"subHeaderText":"@lang.['r','Records']","headerText":"@lang.['dtr01','Drive Time Report']","children":[{"data":[{"buttonType":"secondary","hidden":false,"actionOnClick":["@actions.export","@actions.downloadFile"],"disabled":false,"id":"exportData","type":"button","title":"@lang.['ead1','Export All Data']"}],"type":"actionDropdown","title":"@lang.['ed01','Export Data']","actions":[]}]},"enableSidePanelFilter":false,"isSelectable":false,"dataSource":[],"actions":[{"endPoint":"process/start","alertMessage":true,"name":"export","outputVarMap":{"data":"@pageContext.fileLocationData"},"type":"api","actionDef":{"data":[{"apiResponseParams":["count"],"processId":"exportDriveTimeReportData","apiResponseFormat":true,"contextVar":{"batchSize":50,"getCount":true,"batchNumber":1},"apiResponseObject":"csvurl"}]}},{"name":"downloadFile","type":"script","actionDef":"function(pageContext) {if (typeof pageContext.fileLocationData[0].csvurl !== 'undefined' && pageContext.fileLocationData[0].csvurl !== '') { window.open(pageContext.fileLocationData[0].csvurl); } }"}],"searchKeys":["acFileNumber","address","addressTwo","city","state","postalCode","acReason","acTags","acPrimaryAppraiserId","userName","driveFromAddress","propertyType","startTravelDate","endTravelDate","driveTime","driveDistance"]}