{"processInputData":{"connectors":[{"exitPortType":"NextStep","nodeId":"updateWorkOrderTask"}],"contextChangePermitted":true,"name":"processInputData","description":"processInputData","processRule":"{var scheduledDate = new Date(contextVar.data.startTime); var dueDate = new Date(contextVar.data.endTime); contextVar.estimatedDuration = Math.round( endDate.getTime()- startDate.getTime() )/60000; contextVar.id = contextVar.data.id; contextVar.assignedToUserId = contextVar.data.userId; contextVar.processInstanceId = contextVar.data.instanceId;contextVar.subAction = 'upsertTask';}","nodeType":"PROCESS"},"checkIfInstanceExist":{"connectors":[{"exitPortType":"TrueStep","nodeId":"processInputDataForInstanceUpdate"},{"exitPortType":"FalseStep","nodeId":"end"}],"name":"checkIfInstanceExist","description":"checkIfInstanceExist","processRule":"(contextVar.processInstanceId !== 'undefined' && contextVar.processInstanceId !== '')","nodeType":"DECISION"},"instanceUpdate":{"connectors":[{"exitPortType":"NextStep","nodeId":"end"}],"processId":"RSUFLF8HPK","name":"instanceUpdate","description":"instanceUpdate","inputVarMap":{},"nodeType":"WORKFLOW"},"workflowContext":{},"start":{"connectors":[{"exitPortType":"NextStep","nodeId":"processInputData"}],"name":"start","description":"start","nodeType":"START"},"updateWorkOrderTask":{"connectors":[{"exitPortType":"NextStep","nodeId":"checkIfInstanceExist"}],"processId":"QIFGIU7FDJ","name":"updateWorkOrderTask","description":"updateWorkOrderTask","inputVarMap":{},"nodeType":"WORKFLOW"},"end":{"name":"End","description":"End","processRule":"","nodeType":"END"},"processInputDataForInstanceUpdate":{"connectors":[{"exitPortType":"NextStep","nodeId":"instanceUpdate"}],"contextChangePermitted":true,"name":"processInputDataForInstanceUpdate","description":"processInputDataForInstanceUpdate","processRule":"{var plannedStartTime = new Date(contextVar.data.startTime); var plannedEndTime = new Date(contextVar.data.endTime); contextVar.estimatedDurationInHours = Math.round(estimatedDuration/60); contextVar.id = contextVar.data.id; contextVar.assignedToUserId = contextVar.data.userId; contextVar.instanceId = contextVar.data.instanceId;contextVar.subAction = 'updateInstance';}","nodeType":"PROCESS"},"workflowNodes":["start","processInputData","updateWorkOrderTask","checkIfInstanceExist","processInputDataForInstanceUpdate","instanceUpdate","end"]}