{"upsertWorkOrderTask":{"modelName":"workOrderTask","connectors":[{"exitPortType":"NextStep","nodeId":"end"}],"multirecord":true,"name":"upsertWorkOrderTask","description":"upsertModel","inputVarMap":{"workOrderTask":"data"},"outputVarMap":{"data":"workOrderTaskUpsertedData"},"nodeType":"MODEL","operation":4},"start":{"connectors":[{"exitPortType":"NextStep","nodeId":"checkIfDataPresent"}],"name":"start","description":"Start","nodeType":"START"},"end":{"name":"End","description":"end","inputVarMap":{},"outputVarMap":{},"nodeType":"END"},"workflowNodes":["start","checkIfDataPresent","upsertWorkOrderTask","end"],"checkIfDataPresent":{"connectors":[{"exitPortType":"TrueStep","nodeId":"upsertWorkOrderTask"},{"exitPortType":"FalseStep","nodeId":"end"}],"name":"checkIfDataPresent","description":"checkIfDataPresent","processRule":"typeof contextVar.workOrderTask !== 'undefined' && contextVar.workOrderTask.length>0","nodeType":"DECISION"}}