{"processCatalogData":{"connectors":[{"exitPortType":"NextStep","nodeId":"end"}],"contextChangePermitted":true,"name":"processCatalogData","description":"processCatalogData ","processRule":"{contextVar.catalogId = contextVar.data[0].id}","nodeType":"PROCESS"},"upsertCatalog":{"modelName":"catalog","connectors":[{"exitPortType":"NextStep","nodeId":"processCatalogData"}],"multirecord":true,"name":"upsertCatalog","description":"upsertModel ","inputVarMap":{"catalog":"data"},"outputVarMap":{"data":"data"},"nodeType":"MODEL","operation":4},"start":{"connectors":[{"exitPortType":"NextStep","nodeId":"checkIfDataPresent"}],"name":"start","description":"Start","nodeType":"START"},"end":{"name":"End","description":"end","inputVarMap":{"catalogId":"catalogId"},"outputVarMap":{"catalogId":"catalogId"},"nodeType":"END"},"workflowNodes":["start","checkIfDataPresent","upsertCatalog","processCatalogData","end"],"checkIfDataPresent":{"connectors":[{"exitPortType":"TrueStep","nodeId":"upsertCatalog"},{"exitPortType":"FalseStep","nodeId":"end"}],"name":"checkIfDataPresent","description":"checkIfDataPresent","processRule":"typeof contextVar.catalog !== 'undefined' && contextVar.catalog.length>0","nodeType":"DECISION"}}