{"multiDecision":{"connectors":[{"condition":"contextVar.subAction==='upsertCustomerSite' || contextVar.subAction==='reactivateCustomerSite' || contextVar.subAction==='deactivateCustomerSite'","exitPortType":"NextStep","nodeId":"upsertSite"},{"DefaultStep":true,"condition":"contextVar.subAction===''","exitPortType":"NextStep","nodeId":"end"}],"name":"multiDecision","description":"MultiDecision","nodeType":"MULTIDECISION"},"upsertSite":{"modelName":"site","connectors":[{"exitPortType":"NextStep","nodeId":"processSiteData"}],"multirecord":true,"name":"upsertSite","description":"upsertModel","inputVarMap":{"jsonObj":"data"},"outputVarMap":{"data":"data"},"nodeType":"MODEL","operation":4},"start":{"connectors":[{"exitPortType":"NextStep","nodeId":"processZRule"}],"name":"start","description":"Start","nodeType":"START"},"end":{"name":"end","description":"end","inputVarMap":{"siteId":"siteId"},"outputVarMap":{"siteId":"siteId"},"nodeType":"END"},"processSiteData":{"connectors":[{"exitPortType":"NextStep","nodeId":"end"}],"contextChangePermitted":true,"name":"processSiteData","description":"processSiteData","processRule":"{contextVar.siteId = contextVar.data[0].id}","nodeType":"PROCESS"},"processZRule":{"connectors":[{"exitPortType":"NextStep","nodeId":"multiDecision"}],"contextChangePermitted":true,"name":"processZRule","description":"processZRule","processRule":"@DRT8II70E7","id":"processZRule","nodeType":"PROCESS"},"workflowNodes":["start","processZRule","multiDecision","upsertSite","processSiteData","end"]}